{
    "teams": [
        "d4016",
        "d626b",
        "463da",
        "ba6a6",
        "038da",
        "90e42",
        "b08e9",
        "b6a58",
        "8e758",
        "89518",
        "0a34b",
        "30cd2",
        "cffcc",
        "f7e1f",
        "c4bd0",
        "fff0c",
        "095f7",
        "57819"
    ],
    "tasks": [
        "99763",
        "72340",
        "92945",
        "22453",
        "41246",
        "99496",
        "87826",
        "87551",
        "42384",
        "59373",
        "56051",
        "92343",
        "59363",
        "96016",
        "40116",
        "94604",
        "61289",
        "31704",
        "71088",
        "12589",
        "43870",
        "70105",
        "36295",
        "64898",
        "15446",
        "90402",
        "57164",
        "21467",
        "25257",
        "83804",
        "49197",
        "42173",
        "44958",
        "27188",
        "68253",
        "49144",
        "74982",
        "48255",
        "21885",
        "29750",
        "79606",
        "85221",
        "35003",
        "13161",
        "93636",
        "22890",
        "80717",
        "22343",
        "77646",
        "98192",
        "74697",
        "70080",
        "76451",
        "46714",
        "55775",
        "45428",
        "67169",
        "25043",
        "94747",
        "11591",
        "81167",
        "74736",
        "66854",
        "64323",
        "78295",
        "97497",
        "76983",
        "36338",
        "90652",
        "44026",
        "30521",
        "75961",
        "55487",
        "87417",
        "62259",
        "45650",
        "56437",
        "10741",
        "94947",
        "33955",
        "12262"
    ],
    "calendar": {
        "30cd2": [
            [
                0,
                650
            ]
        ],
        "b08e9": [
            [
                0,
                650
            ]
        ],
        "b6a58": [
            [
                0,
                650
            ]
        ],
        "90e42": [
            [
                0,
                650
            ]
        ],
        "8e758": [
            [
                0,
                650
            ]
        ],
        "095f7": [
            [
                0,
                650
            ]
        ],
        "c4bd0": [
            [
                0,
                650
            ]
        ],
        "038da": [
            [
                0,
                650
            ]
        ],
        "fff0c": [
            [
                0,
                650
            ]
        ],
        "89518": [
            [
                0,
                650
            ]
        ],
        "ba6a6": [
            [
                0,
                650
            ]
        ],
        "f7e1f": [
            [
                0,
                650
            ]
        ],
        "d626b": [
            [
                0,
                650
            ]
        ],
        "463da": [
            [
                0,
                650
            ]
        ],
        "cffcc": [
            [
                0,
                650
            ]
        ],
        "0a34b": [
            [
                0,
                650
            ]
        ],
        "d4016": [
            [
                0,
                960645
            ]
        ],
        "57819": [
            [
                0,
                960645
            ]
        ]
    },
    "teams_to_index": {
        "d4016": 0,
        "d626b": 1,
        "463da": 2,
        "ba6a6": 3,
        "038da": 4,
        "90e42": 5,
        "b08e9": 6,
        "b6a58": 7,
        "8e758": 8,
        "89518": 9,
        "0a34b": 10,
        "30cd2": 11,
        "cffcc": 12,
        "f7e1f": 13,
        "c4bd0": 14,
        "fff0c": 15,
        "095f7": 16
    },
    "tasks_data": {
        "99763": {
            "duration": 15
        },
        "72340": {
            "duration": 30
        },
        "92945": {
            "duration": 45
        },
        "22453": {
            "duration": 45
        },
        "41246": {
            "duration": 45
        },
        "99496": {
            "duration": 14
        },
        "87826": {
            "duration": 30
        },
        "87551": {
            "duration": 15
        },
        "42384": {
            "duration": 30
        },
        "59373": {
            "duration": 30
        },
        "56051": {
            "duration": 15
        },
        "92343": {
            "duration": 15
        },
        "59363": {
            "duration": 30
        },
        "96016": {
            "duration": 45
        },
        "40116": {
            "duration": 30
        },
        "94604": {
            "duration": 15
        },
        "61289": {
            "duration": 30
        },
        "31704": {
            "duration": 60
        },
        "71088": {
            "duration": 30
        },
        "12589": {
            "duration": 45
        },
        "43870": {
            "duration": 30
        },
        "70105": {
            "duration": 30
        },
        "36295": {
            "duration": 15
        },
        "64898": {
            "duration": 45
        },
        "15446": {
            "duration": 60
        },
        "90402": {
            "duration": 15
        },
        "57164": {
            "duration": 15
        },
        "21467": {
            "duration": 60
        },
        "25257": {
            "duration": 45
        },
        "83804": {
            "duration": 30
        },
        "49197": {
            "duration": 15
        },
        "42173": {
            "duration": 30
        },
        "44958": {
            "duration": 75
        },
        "27188": {
            "duration": 45
        },
        "68253": {
            "duration": 30
        },
        "49144": {
            "duration": 15
        },
        "74982": {
            "duration": 15
        },
        "48255": {
            "duration": 15
        },
        "21885": {
            "duration": 15
        },
        "29750": {
            "duration": 15
        },
        "79606": {
            "duration": 30
        },
        "85221": {
            "duration": 30
        },
        "35003": {
            "duration": 15
        },
        "13161": {
            "duration": 75
        },
        "93636": {
            "duration": 30
        },
        "22890": {
            "duration": 45
        },
        "80717": {
            "duration": 30
        },
        "22343": {
            "duration": 75
        },
        "77646": {
            "duration": 15
        },
        "98192": {
            "duration": 30
        },
        "74697": {
            "duration": 60
        },
        "70080": {
            "duration": 30
        },
        "76451": {
            "duration": 45
        },
        "46714": {
            "duration": 30
        },
        "55775": {
            "duration": 45
        },
        "45428": {
            "duration": 15
        },
        "67169": {
            "duration": 30
        },
        "25043": {
            "duration": 30
        },
        "94747": {
            "duration": 75
        },
        "11591": {
            "duration": 15
        },
        "81167": {
            "duration": 45
        },
        "74736": {
            "duration": 45
        },
        "66854": {
            "duration": 15
        },
        "64323": {
            "duration": 60
        },
        "78295": {
            "duration": 30
        },
        "97497": {
            "duration": 15
        },
        "76983": {
            "duration": 15
        },
        "36338": {
            "duration": 15
        },
        "90652": {
            "duration": 15
        },
        "44026": {
            "duration": 30
        },
        "30521": {
            "duration": 30
        },
        "75961": {
            "duration": 15
        },
        "55487": {
            "duration": 15
        },
        "87417": {
            "duration": 45
        },
        "62259": {
            "duration": 15
        },
        "45650": {
            "duration": 15
        },
        "56437": {
            "duration": 75
        },
        "10741": {
            "duration": 15
        },
        "94947": {
            "duration": 45
        },
        "33955": {
            "duration": 30
        },
        "12262": {
            "duration": 30
        }
    },
    "same_allocation": [
        [
            "74697",
            "67169"
        ],
        [
            "67169",
            "66854"
        ],
        [
            "42384",
            "61289"
        ],
        [
            "15446",
            "83804"
        ],
        [
            "76451",
            "77646"
        ],
        [
            "25043",
            "11591"
        ],
        [
            "81167",
            "76983"
        ]
    ],
    "compatible_teams": {
        "94604": [
            "b08e9",
            "30cd2"
        ],
        "43870": [
            "b08e9",
            "30cd2"
        ],
        "49197": [
            "b08e9",
            "30cd2"
        ],
        "48255": [
            "b08e9",
            "30cd2"
        ]
    },
    "start_window": {
        "72340": [
            0,
            30.0
        ],
        "92945": [
            0,
            30.0
        ],
        "22453": [
            0,
            30.0
        ],
        "99763": [
            0,
            35.0
        ],
        "41246": [
            0,
            37.0
        ],
        "87826": [
            1.0,
            61.0
        ],
        "42384": [
            3.0,
            63.0
        ],
        "99496": [
            15.0,
            75.0
        ],
        "59373": [
            15.0,
            75.0
        ],
        "87551": [
            16.0,
            76.0
        ],
        "96016": [
            16.0,
            76.0
        ],
        "31704": [
            17.0,
            77.0
        ],
        "59363": [
            23.0,
            83.0
        ],
        "56051": [
            32.0,
            92.0
        ],
        "92343": [
            33.0,
            93.0
        ],
        "40116": [
            33.0,
            93.0
        ],
        "61289": [
            36.0,
            96.0
        ],
        "12589": [
            48.0,
            108.0
        ],
        "94604": [
            50.0,
            110.0
        ],
        "15446": [
            51.0,
            111.0
        ],
        "71088": [
            54.0,
            114.0
        ],
        "64898": [
            62.0,
            122.0
        ],
        "21467": [
            67.0,
            127.0
        ],
        "43870": [
            70.0,
            130.0
        ],
        "70105": [
            70.0,
            130.0
        ],
        "44958": [
            78.0,
            138.0
        ],
        "36295": [
            85.0,
            145.0
        ],
        "25257": [
            94.0,
            154.0
        ],
        "90402": [
            101.0,
            161.0
        ],
        "57164": [
            103.0,
            163.0
        ],
        "27188": [
            108.0,
            168.0
        ],
        "83804": [
            112.0,
            172.0
        ],
        "42173": [
            117.0,
            177.0
        ],
        "68253": [
            125.0,
            185.0
        ],
        "49197": [
            127.0,
            187.0
        ],
        "13161": [
            129.0,
            189.0
        ],
        "49144": [
            140.0,
            200.0
        ],
        "74982": [
            143.0,
            203.0
        ],
        "48255": [
            143.0,
            203.0
        ],
        "79606": [
            148.0,
            208.0
        ],
        "22343": [
            155.0,
            215.0
        ],
        "21885": [
            156.0,
            216.0
        ],
        "85221": [
            156.0,
            216.0
        ],
        "29750": [
            158.0,
            218.0
        ],
        "22890": [
            172.0,
            232.0
        ],
        "93636": [
            174.0,
            234.0
        ],
        "35003": [
            179.0,
            239.0
        ],
        "80717": [
            187.0,
            247.0
        ],
        "74697": [
            215.0,
            275.0
        ],
        "77646": [
            218.0,
            278.0
        ],
        "98192": [
            218.0,
            278.0
        ],
        "76451": [
            234.0,
            294.0
        ],
        "94747": [
            234.0,
            294.0
        ],
        "70080": [
            247.0,
            307.0
        ],
        "46714": [
            249.0,
            309.0
        ],
        "55775": [
            254.0,
            314.0
        ],
        "64323": [
            271.0,
            331.0
        ],
        "67169": [
            277.0,
            337.0
        ],
        "25043": [
            278.0,
            338.0
        ],
        "81167": [
            280.0,
            340.0
        ],
        "74736": [
            280.0,
            340.0
        ],
        "45428": [
            288.0,
            348.0
        ],
        "78295": [
            304.0,
            364.0
        ],
        "11591": [
            309.0,
            369.0
        ],
        "66854": [
            312.0,
            372.0
        ],
        "56437": [
            315.0,
            375.0
        ],
        "97497": [
            325.0,
            385.0
        ],
        "76983": [
            326.0,
            386.0
        ],
        "44026": [
            328.0,
            388.0
        ],
        "87417": [
            328.0,
            388.0
        ],
        "30521": [
            333.0,
            393.0
        ],
        "36338": [
            335.0,
            395.0
        ],
        "90652": [
            341.0,
            401.0
        ],
        "75961": [
            351.0,
            411.0
        ],
        "55487": [
            357.0,
            417.0
        ],
        "62259": [
            371.0,
            431.0
        ],
        "45650": [
            373.0,
            433.0
        ],
        "94947": [
            374.0,
            434.0
        ],
        "33955": [
            389.0,
            449.0
        ],
        "12262": [
            390.0,
            450.0
        ],
        "10741": [
            395.0,
            455.0
        ]
    },
    "end_window": {
        "72340": [
            0,
            60.0
        ],
        "92945": [
            15.0,
            75.0
        ],
        "22453": [
            15.0,
            75.0
        ],
        "99763": [
            0,
            50.0
        ],
        "41246": [
            22.0,
            82.0
        ],
        "87826": [
            31.0,
            91.0
        ],
        "42384": [
            33.0,
            93.0
        ],
        "99496": [
            29.0,
            89.0
        ],
        "59373": [
            45.0,
            105.0
        ],
        "87551": [
            31.0,
            91.0
        ],
        "96016": [
            61.0,
            121.0
        ],
        "31704": [
            77.0,
            137.0
        ],
        "59363": [
            53.0,
            113.0
        ],
        "56051": [
            47.0,
            107.0
        ],
        "92343": [
            48.0,
            108.0
        ],
        "40116": [
            63.0,
            123.0
        ],
        "61289": [
            66.0,
            126.0
        ],
        "12589": [
            93.0,
            153.0
        ],
        "94604": [
            65.0,
            125.0
        ],
        "15446": [
            111.0,
            171.0
        ],
        "71088": [
            84.0,
            144.0
        ],
        "64898": [
            107.0,
            167.0
        ],
        "21467": [
            127.0,
            187.0
        ],
        "43870": [
            100.0,
            160.0
        ],
        "70105": [
            100.0,
            160.0
        ],
        "44958": [
            153.0,
            213.0
        ],
        "36295": [
            100.0,
            160.0
        ],
        "25257": [
            139.0,
            199.0
        ],
        "90402": [
            116.0,
            176.0
        ],
        "57164": [
            118.0,
            178.0
        ],
        "27188": [
            153.0,
            213.0
        ],
        "83804": [
            142.0,
            202.0
        ],
        "42173": [
            147.0,
            207.0
        ],
        "68253": [
            155.0,
            215.0
        ],
        "49197": [
            142.0,
            202.0
        ],
        "13161": [
            204.0,
            264.0
        ],
        "49144": [
            155.0,
            215.0
        ],
        "74982": [
            158.0,
            218.0
        ],
        "48255": [
            158.0,
            218.0
        ],
        "79606": [
            178.0,
            238.0
        ],
        "22343": [
            230.0,
            290.0
        ],
        "21885": [
            171.0,
            231.0
        ],
        "85221": [
            186.0,
            246.0
        ],
        "29750": [
            173.0,
            233.0
        ],
        "22890": [
            217.0,
            277.0
        ],
        "93636": [
            204.0,
            264.0
        ],
        "35003": [
            194.0,
            254.0
        ],
        "80717": [
            217.0,
            277.0
        ],
        "74697": [
            275.0,
            335.0
        ],
        "77646": [
            233.0,
            293.0
        ],
        "98192": [
            248.0,
            308.0
        ],
        "76451": [
            279.0,
            339.0
        ],
        "94747": [
            309.0,
            369.0
        ],
        "70080": [
            277.0,
            337.0
        ],
        "46714": [
            279.0,
            339.0
        ],
        "55775": [
            299.0,
            359.0
        ],
        "64323": [
            331.0,
            391.0
        ],
        "67169": [
            307.0,
            367.0
        ],
        "25043": [
            308.0,
            368.0
        ],
        "81167": [
            325.0,
            385.0
        ],
        "74736": [
            325.0,
            385.0
        ],
        "45428": [
            303.0,
            363.0
        ],
        "78295": [
            334.0,
            394.0
        ],
        "11591": [
            324.0,
            384.0
        ],
        "66854": [
            327.0,
            387.0
        ],
        "56437": [
            390.0,
            450.0
        ],
        "97497": [
            340.0,
            400.0
        ],
        "76983": [
            341.0,
            401.0
        ],
        "44026": [
            358.0,
            418.0
        ],
        "87417": [
            373.0,
            433.0
        ],
        "30521": [
            363.0,
            423.0
        ],
        "36338": [
            350.0,
            410.0
        ],
        "90652": [
            356.0,
            416.0
        ],
        "75961": [
            366.0,
            426.0
        ],
        "55487": [
            372.0,
            432.0
        ],
        "62259": [
            386.0,
            446.0
        ],
        "45650": [
            388.0,
            448.0
        ],
        "94947": [
            419.0,
            479.0
        ],
        "33955": [
            419.0,
            479.0
        ],
        "12262": [
            420.0,
            480.0
        ],
        "10741": [
            410.0,
            470.0
        ]
    },
    "successors": {
        "99496": [
            "92343"
        ],
        "92343": [
            "15446"
        ],
        "15446": [
            "83804"
        ],
        "83804": [
            "74982"
        ],
        "74982": [
            "29750"
        ],
        "29750": [
            "93636"
        ],
        "49144": [
            "22890"
        ],
        "81167": [
            "76983"
        ],
        "70080": [
            "33955"
        ],
        "72340": [
            "74697"
        ],
        "42384": [
            "61289"
        ],
        "61289": [
            "74697",
            "21467"
        ],
        "74697": [
            "67169"
        ],
        "67169": [
            "66854"
        ],
        "71088": [
            "36295"
        ],
        "36295": [
            "90402"
        ],
        "90402": [
            "42173"
        ],
        "42173": [
            "79606"
        ],
        "13161": [
            "74736"
        ],
        "25043": [
            "11591"
        ],
        "11591": [
            "97497"
        ],
        "87551": [
            "12589"
        ],
        "41246": [
            "35003"
        ],
        "31704": [
            "44958"
        ],
        "44958": [
            "22343"
        ],
        "22343": [
            "94747"
        ],
        "94747": [
            "56437"
        ],
        "92945": [
            "56051"
        ],
        "21467": [
            "13161"
        ],
        "90652": [
            "55487"
        ],
        "55487": [
            "45650"
        ],
        "40116": [
            "70105"
        ],
        "70105": [
            "57164"
        ],
        "57164": [
            "68253"
        ],
        "25257": [
            "21885"
        ],
        "77646": [
            "76451"
        ]
    },
    "horizon_shift": 1754776800,
    "original_start": {
        "72340": 0.0,
        "92945": 0.0,
        "22453": 0.0,
        "99763": 5.0,
        "41246": 7.0,
        "87826": 31.0,
        "42384": 33.0,
        "99496": 45.0,
        "59373": 45.0,
        "87551": 46.0,
        "96016": 46.0,
        "31704": 47.0,
        "59363": 53.0,
        "56051": 62.0,
        "92343": 63.0,
        "40116": 63.0,
        "61289": 66.0,
        "12589": 78.0,
        "94604": 80.0,
        "15446": 81.0,
        "71088": 84.0,
        "64898": 92.0,
        "21467": 97.0,
        "43870": 100.0,
        "70105": 100.0,
        "44958": 108.0,
        "36295": 115.0,
        "25257": 124.0,
        "90402": 131.0,
        "57164": 133.0,
        "27188": 138.0,
        "83804": 142.0,
        "42173": 147.0,
        "68253": 155.0,
        "49197": 157.0,
        "13161": 159.0,
        "49144": 170.0,
        "74982": 173.0,
        "48255": 173.0,
        "79606": 178.0,
        "22343": 185.0,
        "21885": 186.0,
        "85221": 186.0,
        "29750": 188.0,
        "22890": 202.0,
        "93636": 204.0,
        "35003": 209.0,
        "80717": 217.0,
        "74697": 245.0,
        "77646": 248.0,
        "98192": 248.0,
        "76451": 264.0,
        "94747": 264.0,
        "70080": 277.0,
        "46714": 279.0,
        "55775": 284.0,
        "64323": 301.0,
        "67169": 307.0,
        "25043": 308.0,
        "81167": 310.0,
        "74736": 310.0,
        "45428": 318.0,
        "78295": 334.0,
        "11591": 339.0,
        "66854": 342.0,
        "56437": 345.0,
        "97497": 355.0,
        "76983": 356.0,
        "44026": 358.0,
        "87417": 358.0,
        "30521": 363.0,
        "36338": 365.0,
        "90652": 371.0,
        "75961": 381.0,
        "55487": 387.0,
        "62259": 401.0,
        "45650": 403.0,
        "94947": 404.0,
        "33955": 419.0,
        "12262": 420.0,
        "10741": 425.0
    },
    "original_end": {
        "72340": 30.0,
        "92945": 45.0,
        "22453": 45.0,
        "99763": 20.0,
        "41246": 52.0,
        "87826": 61.0,
        "42384": 63.0,
        "99496": 59.0,
        "59373": 75.0,
        "87551": 61.0,
        "96016": 91.0,
        "31704": 107.0,
        "59363": 83.0,
        "56051": 77.0,
        "92343": 78.0,
        "40116": 93.0,
        "61289": 96.0,
        "12589": 123.0,
        "94604": 95.0,
        "15446": 141.0,
        "71088": 114.0,
        "64898": 137.0,
        "21467": 157.0,
        "43870": 130.0,
        "70105": 130.0,
        "44958": 183.0,
        "36295": 130.0,
        "25257": 169.0,
        "90402": 146.0,
        "57164": 148.0,
        "27188": 183.0,
        "83804": 172.0,
        "42173": 177.0,
        "68253": 185.0,
        "49197": 172.0,
        "13161": 234.0,
        "49144": 185.0,
        "74982": 188.0,
        "48255": 188.0,
        "79606": 208.0,
        "22343": 260.0,
        "21885": 201.0,
        "85221": 216.0,
        "29750": 203.0,
        "22890": 247.0,
        "93636": 234.0,
        "35003": 224.0,
        "80717": 247.0,
        "74697": 305.0,
        "77646": 263.0,
        "98192": 278.0,
        "76451": 309.0,
        "94747": 339.0,
        "70080": 307.0,
        "46714": 309.0,
        "55775": 329.0,
        "64323": 361.0,
        "67169": 337.0,
        "25043": 338.0,
        "81167": 355.0,
        "74736": 355.0,
        "45428": 333.0,
        "78295": 364.0,
        "11591": 354.0,
        "66854": 357.0,
        "56437": 420.0,
        "97497": 370.0,
        "76983": 371.0,
        "44026": 388.0,
        "87417": 403.0,
        "30521": 393.0,
        "36338": 380.0,
        "90652": 386.0,
        "75961": 396.0,
        "55487": 402.0,
        "62259": 416.0,
        "45650": 418.0,
        "94947": 449.0,
        "33955": 449.0,
        "12262": 450.0,
        "10741": 440.0
    }
}