{
    "teams": [
        "5ebec",
        "12578",
        "6c981",
        "654c6",
        "fb902",
        "981c2",
        "56ab5",
        "530ac",
        "066af",
        "ff749",
        "540a2",
        "cacb1",
        "238da",
        "87531",
        "0a0dc",
        "3a6bf",
        "f69d4",
        "d1f67",
        "e536f",
        "4ebc9"
    ],
    "tasks": [
        "65256",
        "43347",
        "86987",
        "38368",
        "35462",
        "42519",
        "61661",
        "15520",
        "20017",
        "40801",
        "23365",
        "67150",
        "56153",
        "41055",
        "31112",
        "93548",
        "52837",
        "24911",
        "29599",
        "30585",
        "89909",
        "50542",
        "31133",
        "22453",
        "82260",
        "48292",
        "63985",
        "30735",
        "45054",
        "97602",
        "71386",
        "13803",
        "45559",
        "57396",
        "64363",
        "67756",
        "71567",
        "30853",
        "67513",
        "61568",
        "37463",
        "57984",
        "28477",
        "33622",
        "85211",
        "24157",
        "66427",
        "84325",
        "38288",
        "18715",
        "59359",
        "35371",
        "14471",
        "96979",
        "38935",
        "96343",
        "84261",
        "84678",
        "78515",
        "14229",
        "58539",
        "62954",
        "33448",
        "61850",
        "58345",
        "91597",
        "36093",
        "92700",
        "19620",
        "63924",
        "75975",
        "26837",
        "47585",
        "62598",
        "21403",
        "13199",
        "14282",
        "16609",
        "99749",
        "30493",
        "54396",
        "97601",
        "83099",
        "45242",
        "47469",
        "26028",
        "21375",
        "21925",
        "32909",
        "50254",
        "45302",
        "28094",
        "59848",
        "57285",
        "83189",
        "70647",
        "98594",
        "68374",
        "93292",
        "41875",
        "51629",
        "35803"
    ],
    "calendar": {
        "3a6bf": [
            [
                0,
                660
            ]
        ],
        "12578": [
            [
                0,
                660
            ]
        ],
        "238da": [
            [
                0,
                660
            ]
        ],
        "530ac": [
            [
                0,
                660
            ]
        ],
        "066af": [
            [
                0,
                660
            ]
        ],
        "56ab5": [
            [
                0,
                660
            ]
        ],
        "ff749": [
            [
                0,
                660
            ]
        ],
        "e536f": [
            [
                0,
                660
            ]
        ],
        "f69d4": [
            [
                0,
                660
            ]
        ],
        "981c2": [
            [
                0,
                660
            ]
        ],
        "d1f67": [
            [
                0,
                660
            ]
        ],
        "540a2": [
            [
                0,
                660
            ]
        ],
        "fb902": [
            [
                0,
                660
            ]
        ],
        "0a0dc": [
            [
                0,
                660
            ]
        ],
        "6c981": [
            [
                0,
                660
            ]
        ],
        "654c6": [
            [
                0,
                660
            ]
        ],
        "87531": [
            [
                0,
                660
            ]
        ],
        "cacb1": [
            [
                0,
                660
            ]
        ],
        "5ebec": [
            [
                0,
                680
            ]
        ],
        "4ebc9": [
            [
                0,
                680
            ]
        ]
    },
    "teams_to_index": {
        "5ebec": 0,
        "12578": 1,
        "6c981": 2,
        "654c6": 3,
        "fb902": 4,
        "981c2": 5,
        "56ab5": 6,
        "530ac": 7,
        "066af": 8,
        "ff749": 9,
        "540a2": 10,
        "cacb1": 11,
        "238da": 12,
        "87531": 13,
        "0a0dc": 14,
        "3a6bf": 15,
        "f69d4": 16,
        "d1f67": 17,
        "e536f": 18
    },
    "tasks_data": {
        "65256": {
            "duration": 30
        },
        "43347": {
            "duration": 30
        },
        "86987": {
            "duration": 45
        },
        "38368": {
            "duration": 30
        },
        "35462": {
            "duration": 15
        },
        "42519": {
            "duration": 31
        },
        "61661": {
            "duration": 15
        },
        "15520": {
            "duration": 45
        },
        "20017": {
            "duration": 15
        },
        "40801": {
            "duration": 30
        },
        "23365": {
            "duration": 60
        },
        "67150": {
            "duration": 15
        },
        "56153": {
            "duration": 30
        },
        "41055": {
            "duration": 15
        },
        "31112": {
            "duration": 60
        },
        "93548": {
            "duration": 45
        },
        "52837": {
            "duration": 30
        },
        "24911": {
            "duration": 15
        },
        "29599": {
            "duration": 45
        },
        "30585": {
            "duration": 15
        },
        "89909": {
            "duration": 60
        },
        "50542": {
            "duration": 15
        },
        "31133": {
            "duration": 15
        },
        "22453": {
            "duration": 15
        },
        "82260": {
            "duration": 30
        },
        "48292": {
            "duration": 15
        },
        "63985": {
            "duration": 60
        },
        "30735": {
            "duration": 15
        },
        "45054": {
            "duration": 15
        },
        "97602": {
            "duration": 60
        },
        "71386": {
            "duration": 45
        },
        "13803": {
            "duration": 60
        },
        "45559": {
            "duration": 15
        },
        "57396": {
            "duration": 30
        },
        "64363": {
            "duration": 30
        },
        "67756": {
            "duration": 30
        },
        "71567": {
            "duration": 15
        },
        "30853": {
            "duration": 45
        },
        "67513": {
            "duration": 15
        },
        "61568": {
            "duration": 30
        },
        "37463": {
            "duration": 60
        },
        "57984": {
            "duration": 60
        },
        "28477": {
            "duration": 15
        },
        "33622": {
            "duration": 60
        },
        "85211": {
            "duration": 60
        },
        "24157": {
            "duration": 30
        },
        "66427": {
            "duration": 15
        },
        "84325": {
            "duration": 15
        },
        "38288": {
            "duration": 15
        },
        "18715": {
            "duration": 15
        },
        "59359": {
            "duration": 30
        },
        "35371": {
            "duration": 30
        },
        "14471": {
            "duration": 45
        },
        "96979": {
            "duration": 45
        },
        "38935": {
            "duration": 45
        },
        "96343": {
            "duration": 60
        },
        "84261": {
            "duration": 30
        },
        "84678": {
            "duration": 15
        },
        "78515": {
            "duration": 30
        },
        "14229": {
            "duration": 30
        },
        "58539": {
            "duration": 30
        },
        "62954": {
            "duration": 30
        },
        "33448": {
            "duration": 30
        },
        "61850": {
            "duration": 45
        },
        "58345": {
            "duration": 30
        },
        "91597": {
            "duration": 30
        },
        "36093": {
            "duration": 30
        },
        "92700": {
            "duration": 45
        },
        "19620": {
            "duration": 30
        },
        "63924": {
            "duration": 30
        },
        "75975": {
            "duration": 30
        },
        "26837": {
            "duration": 30
        },
        "47585": {
            "duration": 30
        },
        "62598": {
            "duration": 15
        },
        "21403": {
            "duration": 15
        },
        "13199": {
            "duration": 15
        },
        "14282": {
            "duration": 15
        },
        "16609": {
            "duration": 30
        },
        "99749": {
            "duration": 15
        },
        "30493": {
            "duration": 30
        },
        "54396": {
            "duration": 45
        },
        "97601": {
            "duration": 30
        },
        "83099": {
            "duration": 30
        },
        "45242": {
            "duration": 30
        },
        "47469": {
            "duration": 30
        },
        "26028": {
            "duration": 60
        },
        "21375": {
            "duration": 30
        },
        "21925": {
            "duration": 45
        },
        "32909": {
            "duration": 30
        },
        "50254": {
            "duration": 30
        },
        "45302": {
            "duration": 45
        },
        "28094": {
            "duration": 15
        },
        "59848": {
            "duration": 30
        },
        "57285": {
            "duration": 45
        },
        "83189": {
            "duration": 30
        },
        "70647": {
            "duration": 45
        },
        "98594": {
            "duration": 15
        },
        "68374": {
            "duration": 60
        },
        "93292": {
            "duration": 15
        },
        "41875": {
            "duration": 45
        },
        "51629": {
            "duration": 15
        },
        "35803": {
            "duration": 15
        }
    },
    "same_allocation": [
        [
            "40801",
            "43347"
        ],
        [
            "38368",
            "20017"
        ],
        [
            "31112",
            "13803"
        ],
        [
            "35462",
            "93548"
        ],
        [
            "93548",
            "50542"
        ],
        [
            "35371",
            "33622"
        ],
        [
            "52837",
            "82260"
        ],
        [
            "24911",
            "71386"
        ],
        [
            "64363",
            "48292"
        ],
        [
            "30853",
            "24157"
        ],
        [
            "24157",
            "38288"
        ],
        [
            "45559",
            "61568"
        ],
        [
            "66427",
            "61568"
        ],
        [
            "83099",
            "50254"
        ],
        [
            "99749",
            "21925"
        ],
        [
            "70647",
            "51629"
        ]
    ],
    "compatible_teams": {
        "65256": [
            "238da",
            "530ac"
        ],
        "42519": [
            "238da",
            "530ac"
        ]
    },
    "start_window": {
        "65256": [
            0,
            30.0
        ],
        "86987": [
            0,
            41.0
        ],
        "43347": [
            0,
            42.0
        ],
        "23365": [
            0,
            47.0
        ],
        "15520": [
            0,
            55.0
        ],
        "38368": [
            0,
            56.0
        ],
        "31112": [
            3.0,
            63.0
        ],
        "42519": [
            5.0,
            65.0
        ],
        "35462": [
            11.0,
            71.0
        ],
        "40801": [
            13.0,
            73.0
        ],
        "61661": [
            24.0,
            84.0
        ],
        "89909": [
            24.0,
            84.0
        ],
        "93548": [
            26.0,
            86.0
        ],
        "20017": [
            27.0,
            87.0
        ],
        "56153": [
            27.0,
            87.0
        ],
        "29599": [
            27.0,
            87.0
        ],
        "67150": [
            40.0,
            100.0
        ],
        "52837": [
            41.0,
            101.0
        ],
        "41055": [
            43.0,
            103.0
        ],
        "63985": [
            44.0,
            104.0
        ],
        "97602": [
            48.0,
            108.0
        ],
        "24911": [
            56.0,
            116.0
        ],
        "30585": [
            59.0,
            119.0
        ],
        "13803": [
            64.0,
            124.0
        ],
        "50542": [
            72.0,
            132.0
        ],
        "82260": [
            72.0,
            132.0
        ],
        "31133": [
            73.0,
            133.0
        ],
        "71386": [
            74.0,
            134.0
        ],
        "22453": [
            75.0,
            135.0
        ],
        "48292": [
            88.0,
            148.0
        ],
        "30735": [
            89.0,
            149.0
        ],
        "45054": [
            91.0,
            151.0
        ],
        "57396": [
            103.0,
            163.0
        ],
        "64363": [
            104.0,
            164.0
        ],
        "30853": [
            105.0,
            165.0
        ],
        "67756": [
            107.0,
            167.0
        ],
        "37463": [
            109.0,
            169.0
        ],
        "57984": [
            109.0,
            169.0
        ],
        "45559": [
            116.0,
            176.0
        ],
        "33622": [
            120.0,
            180.0
        ],
        "85211": [
            120.0,
            180.0
        ],
        "71567": [
            132.0,
            192.0
        ],
        "61568": [
            135.0,
            195.0
        ],
        "67513": [
            148.0,
            208.0
        ],
        "24157": [
            151.0,
            211.0
        ],
        "28477": [
            164.0,
            224.0
        ],
        "66427": [
            166.0,
            226.0
        ],
        "14471": [
            170.0,
            230.0
        ],
        "96343": [
            170.0,
            230.0
        ],
        "84325": [
            180.0,
            240.0
        ],
        "96979": [
            181.0,
            241.0
        ],
        "38288": [
            182.0,
            242.0
        ],
        "59359": [
            182.0,
            242.0
        ],
        "38935": [
            182.0,
            242.0
        ],
        "35371": [
            184.0,
            244.0
        ],
        "18715": [
            196.0,
            256.0
        ],
        "84261": [
            202.0,
            262.0
        ],
        "78515": [
            212.0,
            272.0
        ],
        "14229": [
            213.0,
            273.0
        ],
        "84678": [
            218.0,
            278.0
        ],
        "61850": [
            227.0,
            287.0
        ],
        "58539": [
            228.0,
            288.0
        ],
        "62954": [
            233.0,
            293.0
        ],
        "33448": [
            237.0,
            297.0
        ],
        "58345": [
            243.0,
            303.0
        ],
        "91597": [
            244.0,
            304.0
        ],
        "92700": [
            248.0,
            308.0
        ],
        "36093": [
            259.0,
            319.0
        ],
        "19620": [
            264.0,
            324.0
        ],
        "63924": [
            272.0,
            332.0
        ],
        "75975": [
            274.0,
            334.0
        ],
        "26837": [
            275.0,
            335.0
        ],
        "47585": [
            275.0,
            335.0
        ],
        "62598": [
            290.0,
            350.0
        ],
        "54396": [
            294.0,
            354.0
        ],
        "16609": [
            295.0,
            355.0
        ],
        "26028": [
            305.0,
            365.0
        ],
        "21403": [
            306.0,
            366.0
        ],
        "13199": [
            306.0,
            366.0
        ],
        "14282": [
            306.0,
            366.0
        ],
        "30493": [
            308.0,
            368.0
        ],
        "99749": [
            322.0,
            382.0
        ],
        "97601": [
            322.0,
            382.0
        ],
        "83099": [
            322.0,
            382.0
        ],
        "45242": [
            326.0,
            386.0
        ],
        "47469": [
            329.0,
            389.0
        ],
        "21925": [
            338.0,
            398.0
        ],
        "21375": [
            339.0,
            399.0
        ],
        "45302": [
            340.0,
            400.0
        ],
        "32909": [
            353.0,
            413.0
        ],
        "50254": [
            353.0,
            413.0
        ],
        "57285": [
            357.0,
            417.0
        ],
        "68374": [
            366.0,
            426.0
        ],
        "59848": [
            370.0,
            430.0
        ],
        "70647": [
            370.0,
            430.0
        ],
        "28094": [
            384.0,
            444.0
        ],
        "83189": [
            384.0,
            444.0
        ],
        "41875": [
            386.0,
            446.0
        ],
        "98594": [
            400.0,
            460.0
        ],
        "93292": [
            415.0,
            475.0
        ],
        "51629": [
            416.0,
            476.0
        ],
        "35803": [
            416.0,
            476.0
        ]
    },
    "end_window": {
        "65256": [
            0,
            60.0
        ],
        "86987": [
            26.0,
            86.0
        ],
        "43347": [
            12.0,
            72.0
        ],
        "23365": [
            47.0,
            107.0
        ],
        "15520": [
            40.0,
            100.0
        ],
        "38368": [
            26.0,
            86.0
        ],
        "31112": [
            63.0,
            123.0
        ],
        "42519": [
            36.0,
            96.0
        ],
        "35462": [
            26.0,
            86.0
        ],
        "40801": [
            43.0,
            103.0
        ],
        "61661": [
            39.0,
            99.0
        ],
        "89909": [
            84.0,
            144.0
        ],
        "93548": [
            71.0,
            131.0
        ],
        "20017": [
            42.0,
            102.0
        ],
        "56153": [
            57.0,
            117.0
        ],
        "29599": [
            72.0,
            132.0
        ],
        "67150": [
            55.0,
            115.0
        ],
        "52837": [
            71.0,
            131.0
        ],
        "41055": [
            58.0,
            118.0
        ],
        "63985": [
            104.0,
            164.0
        ],
        "97602": [
            108.0,
            168.0
        ],
        "24911": [
            71.0,
            131.0
        ],
        "30585": [
            74.0,
            134.0
        ],
        "13803": [
            124.0,
            184.0
        ],
        "50542": [
            87.0,
            147.0
        ],
        "82260": [
            102.0,
            162.0
        ],
        "31133": [
            88.0,
            148.0
        ],
        "71386": [
            119.0,
            179.0
        ],
        "22453": [
            90.0,
            150.0
        ],
        "48292": [
            103.0,
            163.0
        ],
        "30735": [
            104.0,
            164.0
        ],
        "45054": [
            106.0,
            166.0
        ],
        "57396": [
            133.0,
            193.0
        ],
        "64363": [
            134.0,
            194.0
        ],
        "30853": [
            150.0,
            210.0
        ],
        "67756": [
            137.0,
            197.0
        ],
        "37463": [
            169.0,
            229.0
        ],
        "57984": [
            169.0,
            229.0
        ],
        "45559": [
            131.0,
            191.0
        ],
        "33622": [
            180.0,
            240.0
        ],
        "85211": [
            180.0,
            240.0
        ],
        "71567": [
            147.0,
            207.0
        ],
        "61568": [
            165.0,
            225.0
        ],
        "67513": [
            163.0,
            223.0
        ],
        "24157": [
            181.0,
            241.0
        ],
        "28477": [
            179.0,
            239.0
        ],
        "66427": [
            181.0,
            241.0
        ],
        "14471": [
            215.0,
            275.0
        ],
        "96343": [
            230.0,
            290.0
        ],
        "84325": [
            195.0,
            255.0
        ],
        "96979": [
            226.0,
            286.0
        ],
        "38288": [
            197.0,
            257.0
        ],
        "59359": [
            212.0,
            272.0
        ],
        "38935": [
            227.0,
            287.0
        ],
        "35371": [
            214.0,
            274.0
        ],
        "18715": [
            211.0,
            271.0
        ],
        "84261": [
            232.0,
            292.0
        ],
        "78515": [
            242.0,
            302.0
        ],
        "14229": [
            243.0,
            303.0
        ],
        "84678": [
            233.0,
            293.0
        ],
        "61850": [
            272.0,
            332.0
        ],
        "58539": [
            258.0,
            318.0
        ],
        "62954": [
            263.0,
            323.0
        ],
        "33448": [
            267.0,
            327.0
        ],
        "58345": [
            273.0,
            333.0
        ],
        "91597": [
            274.0,
            334.0
        ],
        "92700": [
            293.0,
            353.0
        ],
        "36093": [
            289.0,
            349.0
        ],
        "19620": [
            294.0,
            354.0
        ],
        "63924": [
            302.0,
            362.0
        ],
        "75975": [
            304.0,
            364.0
        ],
        "26837": [
            305.0,
            365.0
        ],
        "47585": [
            305.0,
            365.0
        ],
        "62598": [
            305.0,
            365.0
        ],
        "54396": [
            339.0,
            399.0
        ],
        "16609": [
            325.0,
            385.0
        ],
        "26028": [
            365.0,
            425.0
        ],
        "21403": [
            321.0,
            381.0
        ],
        "13199": [
            321.0,
            381.0
        ],
        "14282": [
            321.0,
            381.0
        ],
        "30493": [
            338.0,
            398.0
        ],
        "99749": [
            337.0,
            397.0
        ],
        "97601": [
            352.0,
            412.0
        ],
        "83099": [
            352.0,
            412.0
        ],
        "45242": [
            356.0,
            416.0
        ],
        "47469": [
            359.0,
            419.0
        ],
        "21925": [
            383.0,
            443.0
        ],
        "21375": [
            369.0,
            429.0
        ],
        "45302": [
            385.0,
            445.0
        ],
        "32909": [
            383.0,
            443.0
        ],
        "50254": [
            383.0,
            443.0
        ],
        "57285": [
            402.0,
            462.0
        ],
        "68374": [
            426.0,
            486.0
        ],
        "59848": [
            400.0,
            460.0
        ],
        "70647": [
            415.0,
            475.0
        ],
        "28094": [
            399.0,
            459.0
        ],
        "83189": [
            414.0,
            474.0
        ],
        "41875": [
            431.0,
            491.0
        ],
        "98594": [
            415.0,
            475.0
        ],
        "93292": [
            430.0,
            490.0
        ],
        "51629": [
            431.0,
            491.0
        ],
        "35803": [
            431.0,
            491.0
        ]
    },
    "successors": {
        "99749": [
            "21925"
        ],
        "48292": [
            "64363"
        ],
        "70647": [
            "51629"
        ],
        "84325": [
            "18715"
        ],
        "18715": [
            "78515"
        ],
        "93548": [
            "50542"
        ],
        "33622": [
            "35371"
        ],
        "35371": [
            "84678"
        ],
        "84678": [
            "33448"
        ],
        "33448": [
            "63924"
        ],
        "50254": [
            "35803"
        ],
        "28094": [
            "98594"
        ],
        "98594": [
            "35803"
        ],
        "58539": [
            "83189"
        ],
        "38935": [
            "93292"
        ],
        "31112": [
            "13803"
        ],
        "24911": [
            "71386"
        ],
        "52837": [
            "82260"
        ],
        "45559": [
            "71567"
        ],
        "61568": [
            "66427"
        ],
        "14229": [
            "91597"
        ],
        "91597": [
            "47585"
        ],
        "47585": [
            "14282"
        ],
        "67513": [
            "28477"
        ],
        "58345": [
            "26028"
        ],
        "75975": [
            "68374"
        ],
        "86987": [
            "29599"
        ],
        "29599": [
            "31133"
        ],
        "31133": [
            "30735"
        ],
        "30735": [
            "30853"
        ],
        "30853": [
            "24157"
        ],
        "24157": [
            "38288"
        ],
        "43347": [
            "40801"
        ],
        "36093": [
            "62598"
        ],
        "62598": [
            "21403"
        ],
        "21403": [
            "97601"
        ],
        "97601": [
            "32909"
        ],
        "38368": [
            "20017"
        ],
        "20017": [
            "41055"
        ]
    },
    "horizon_shift": 1754776800,
    "original_start": {
        "65256": 0.0,
        "86987": 11.0,
        "43347": 12.0,
        "23365": 17.0,
        "15520": 25.0,
        "38368": 26.0,
        "31112": 33.0,
        "42519": 35.0,
        "35462": 41.0,
        "40801": 43.0,
        "61661": 54.0,
        "89909": 54.0,
        "93548": 56.0,
        "20017": 57.0,
        "56153": 57.0,
        "29599": 57.0,
        "67150": 70.0,
        "52837": 71.0,
        "41055": 73.0,
        "63985": 74.0,
        "97602": 78.0,
        "24911": 86.0,
        "30585": 89.0,
        "13803": 94.0,
        "50542": 102.0,
        "82260": 102.0,
        "31133": 103.0,
        "71386": 104.0,
        "22453": 105.0,
        "48292": 118.0,
        "30735": 119.0,
        "45054": 121.0,
        "57396": 133.0,
        "64363": 134.0,
        "30853": 135.0,
        "67756": 137.0,
        "37463": 139.0,
        "57984": 139.0,
        "45559": 146.0,
        "33622": 150.0,
        "85211": 150.0,
        "71567": 162.0,
        "61568": 165.0,
        "67513": 178.0,
        "24157": 181.0,
        "28477": 194.0,
        "66427": 196.0,
        "14471": 200.0,
        "96343": 200.0,
        "84325": 210.0,
        "96979": 211.0,
        "38288": 212.0,
        "59359": 212.0,
        "38935": 212.0,
        "35371": 214.0,
        "18715": 226.0,
        "84261": 232.0,
        "78515": 242.0,
        "14229": 243.0,
        "84678": 248.0,
        "61850": 257.0,
        "58539": 258.0,
        "62954": 263.0,
        "33448": 267.0,
        "58345": 273.0,
        "91597": 274.0,
        "92700": 278.0,
        "36093": 289.0,
        "19620": 294.0,
        "63924": 302.0,
        "75975": 304.0,
        "26837": 305.0,
        "47585": 305.0,
        "62598": 320.0,
        "54396": 324.0,
        "16609": 325.0,
        "26028": 335.0,
        "21403": 336.0,
        "13199": 336.0,
        "14282": 336.0,
        "30493": 338.0,
        "99749": 352.0,
        "97601": 352.0,
        "83099": 352.0,
        "45242": 356.0,
        "47469": 359.0,
        "21925": 368.0,
        "21375": 369.0,
        "45302": 370.0,
        "32909": 383.0,
        "50254": 383.0,
        "57285": 387.0,
        "68374": 396.0,
        "59848": 400.0,
        "70647": 400.0,
        "28094": 414.0,
        "83189": 414.0,
        "41875": 416.0,
        "98594": 430.0,
        "93292": 445.0,
        "51629": 446.0,
        "35803": 446.0
    },
    "original_end": {
        "65256": 30.0,
        "86987": 56.0,
        "43347": 42.0,
        "23365": 77.0,
        "15520": 70.0,
        "38368": 56.0,
        "31112": 93.0,
        "42519": 66.0,
        "35462": 56.0,
        "40801": 73.0,
        "61661": 69.0,
        "89909": 114.0,
        "93548": 101.0,
        "20017": 72.0,
        "56153": 87.0,
        "29599": 102.0,
        "67150": 85.0,
        "52837": 101.0,
        "41055": 88.0,
        "63985": 134.0,
        "97602": 138.0,
        "24911": 101.0,
        "30585": 104.0,
        "13803": 154.0,
        "50542": 117.0,
        "82260": 132.0,
        "31133": 118.0,
        "71386": 149.0,
        "22453": 120.0,
        "48292": 133.0,
        "30735": 134.0,
        "45054": 136.0,
        "57396": 163.0,
        "64363": 164.0,
        "30853": 180.0,
        "67756": 167.0,
        "37463": 199.0,
        "57984": 199.0,
        "45559": 161.0,
        "33622": 210.0,
        "85211": 210.0,
        "71567": 177.0,
        "61568": 195.0,
        "67513": 193.0,
        "24157": 211.0,
        "28477": 209.0,
        "66427": 211.0,
        "14471": 245.0,
        "96343": 260.0,
        "84325": 225.0,
        "96979": 256.0,
        "38288": 227.0,
        "59359": 242.0,
        "38935": 257.0,
        "35371": 244.0,
        "18715": 241.0,
        "84261": 262.0,
        "78515": 272.0,
        "14229": 273.0,
        "84678": 263.0,
        "61850": 302.0,
        "58539": 288.0,
        "62954": 293.0,
        "33448": 297.0,
        "58345": 303.0,
        "91597": 304.0,
        "92700": 323.0,
        "36093": 319.0,
        "19620": 324.0,
        "63924": 332.0,
        "75975": 334.0,
        "26837": 335.0,
        "47585": 335.0,
        "62598": 335.0,
        "54396": 369.0,
        "16609": 355.0,
        "26028": 395.0,
        "21403": 351.0,
        "13199": 351.0,
        "14282": 351.0,
        "30493": 368.0,
        "99749": 367.0,
        "97601": 382.0,
        "83099": 382.0,
        "45242": 386.0,
        "47469": 389.0,
        "21925": 413.0,
        "21375": 399.0,
        "45302": 415.0,
        "32909": 413.0,
        "50254": 413.0,
        "57285": 432.0,
        "68374": 456.0,
        "59848": 430.0,
        "70647": 445.0,
        "28094": 429.0,
        "83189": 444.0,
        "41875": 461.0,
        "98594": 445.0,
        "93292": 460.0,
        "51629": 461.0,
        "35803": 461.0
    },
    "disruption": {
        "type": "resource",
        "disruptions": [
            [
                241,
                256,
                9
            ],
            [
                241,
                256,
                10
            ],
            [
                241,
                256,
                3
            ],
            [
                241,
                256,
                8
            ],
            [
                241,
                256,
                11
            ],
            [
                241,
                256,
                5
            ],
            [
                241,
                256,
                6
            ],
            [
                241,
                256,
                4
            ],
            [
                73,
                193,
                6
            ],
            [
                73,
                193,
                2
            ],
            [
                73,
                193,
                5
            ],
            [
                73,
                193,
                0
            ],
            [
                73,
                193,
                3
            ],
            [
                334,
                454,
                6
            ],
            [
                334,
                454,
                9
            ],
            [
                334,
                454,
                8
            ],
            [
                334,
                454,
                7
            ],
            [
                334,
                454,
                0
            ],
            [
                334,
                454,
                10
            ],
            [
                334,
                454,
                11
            ],
            [
                334,
                454,
                5
            ],
            [
                334,
                454,
                2
            ],
            [
                214,
                334,
                3
            ],
            [
                214,
                334,
                10
            ],
            [
                214,
                334,
                7
            ],
            [
                183,
                243,
                6
            ],
            [
                145,
                205,
                6
            ],
            [
                145,
                205,
                0
            ],
            [
                303,
                333,
                10
            ],
            [
                303,
                333,
                8
            ],
            [
                303,
                333,
                5
            ],
            [
                303,
                333,
                7
            ],
            [
                303,
                333,
                9
            ],
            [
                303,
                333,
                4
            ],
            [
                303,
                333,
                0
            ],
            [
                303,
                333,
                3
            ],
            [
                174,
                234,
                8
            ],
            [
                174,
                234,
                2
            ],
            [
                174,
                234,
                7
            ],
            [
                174,
                234,
                5
            ],
            [
                174,
                234,
                0
            ],
            [
                174,
                234,
                4
            ],
            [
                42,
                57,
                10
            ],
            [
                42,
                57,
                2
            ],
            [
                42,
                57,
                3
            ]
        ]
    },
    "base_solution": {
        "allocation": [
            7,
            0,
            6,
            11,
            8,
            7,
            5,
            9,
            11,
            0,
            3,
            7,
            6,
            11,
            10,
            8,
            5,
            3,
            2,
            7,
            4,
            8,
            6,
            2,
            5,
            11,
            9,
            4,
            2,
            0,
            3,
            10,
            9,
            7,
            11,
            6,
            3,
            5,
            3,
            9,
            4,
            0,
            3,
            8,
            2,
            5,
            9,
            4,
            5,
            4,
            3,
            8,
            0,
            6,
            2,
            7,
            5,
            0,
            4,
            3,
            2,
            0,
            7,
            6,
            5,
            3,
            2,
            4,
            0,
            7,
            6,
            5,
            3,
            2,
            7,
            6,
            5,
            4,
            8,
            2,
            0,
            5,
            7,
            6,
            4,
            3,
            2,
            8,
            5,
            7,
            0,
            7,
            2,
            6,
            5,
            4,
            2,
            3,
            2,
            0,
            4,
            7
        ],
        "schedule": [
            [
                0,
                30
            ],
            [
                12,
                42
            ],
            [
                11,
                56
            ],
            [
                26,
                56
            ],
            [
                41,
                56
            ],
            [
                35,
                66
            ],
            [
                54,
                69
            ],
            [
                25,
                70
            ],
            [
                57,
                72
            ],
            [
                43,
                73
            ],
            [
                17,
                77
            ],
            [
                70,
                85
            ],
            [
                57,
                87
            ],
            [
                73,
                88
            ],
            [
                33,
                93
            ],
            [
                56,
                101
            ],
            [
                71,
                101
            ],
            [
                86,
                101
            ],
            [
                57,
                102
            ],
            [
                89,
                104
            ],
            [
                54,
                114
            ],
            [
                102,
                117
            ],
            [
                103,
                118
            ],
            [
                105,
                120
            ],
            [
                102,
                132
            ],
            [
                118,
                133
            ],
            [
                74,
                134
            ],
            [
                119,
                134
            ],
            [
                121,
                136
            ],
            [
                78,
                138
            ],
            [
                104,
                149
            ],
            [
                94,
                154
            ],
            [
                146,
                161
            ],
            [
                133,
                163
            ],
            [
                134,
                164
            ],
            [
                137,
                167
            ],
            [
                162,
                177
            ],
            [
                135,
                180
            ],
            [
                178,
                193
            ],
            [
                165,
                195
            ],
            [
                139,
                199
            ],
            [
                139,
                199
            ],
            [
                194,
                209
            ],
            [
                150,
                210
            ],
            [
                150,
                210
            ],
            [
                181,
                211
            ],
            [
                196,
                211
            ],
            [
                210,
                225
            ],
            [
                212,
                227
            ],
            [
                226,
                241
            ],
            [
                212,
                242
            ],
            [
                214,
                244
            ],
            [
                200,
                245
            ],
            [
                211,
                256
            ],
            [
                212,
                257
            ],
            [
                200,
                260
            ],
            [
                232,
                262
            ],
            [
                248,
                263
            ],
            [
                242,
                272
            ],
            [
                243,
                273
            ],
            [
                258,
                288
            ],
            [
                263,
                293
            ],
            [
                267,
                297
            ],
            [
                257,
                302
            ],
            [
                273,
                303
            ],
            [
                274,
                304
            ],
            [
                289,
                319
            ],
            [
                278,
                323
            ],
            [
                294,
                324
            ],
            [
                302,
                332
            ],
            [
                304,
                334
            ],
            [
                305,
                335
            ],
            [
                305,
                335
            ],
            [
                320,
                335
            ],
            [
                336,
                351
            ],
            [
                336,
                351
            ],
            [
                336,
                351
            ],
            [
                325,
                355
            ],
            [
                352,
                367
            ],
            [
                338,
                368
            ],
            [
                324,
                369
            ],
            [
                352,
                382
            ],
            [
                352,
                382
            ],
            [
                356,
                386
            ],
            [
                359,
                389
            ],
            [
                335,
                395
            ],
            [
                369,
                399
            ],
            [
                368,
                413
            ],
            [
                383,
                413
            ],
            [
                383,
                413
            ],
            [
                370,
                415
            ],
            [
                414,
                429
            ],
            [
                400,
                430
            ],
            [
                387,
                432
            ],
            [
                414,
                444
            ],
            [
                400,
                445
            ],
            [
                430,
                445
            ],
            [
                396,
                456
            ],
            [
                445,
                460
            ],
            [
                416,
                461
            ],
            [
                446,
                461
            ],
            [
                446,
                461
            ]
        ]
    },
    "additional_constraint": {
        "nb_teams_bounds": [
            null,
            11
        ],
        "team_used_constraint": {
            "0": null,
            "1": false,
            "2": null,
            "3": null,
            "4": null,
            "5": null,
            "6": null,
            "7": null,
            "8": null,
            "9": null,
            "10": null,
            "11": null,
            "12": false,
            "13": false,
            "14": false,
            "15": false,
            "16": false,
            "17": false,
            "18": false,
            "19": false
        }
    }
}