{
    "teams": [
        "e269b",
        "2923b",
        "46a8d",
        "9ef6a",
        "f7b98",
        "bbed0",
        "93239",
        "a80d7",
        "80258",
        "ab78a",
        "6615f",
        "3f926",
        "1e5be",
        "414c9",
        "b8747",
        "830b6",
        "8533f",
        "111a9"
    ],
    "tasks": [
        "14868",
        "31859",
        "92149",
        "56141",
        "77346",
        "45902",
        "50400",
        "82146",
        "93256",
        "19282",
        "51523",
        "47020",
        "22302",
        "22540",
        "80295",
        "15242",
        "12121",
        "99407",
        "36266",
        "66962",
        "96942",
        "90528",
        "20328",
        "88985",
        "78704",
        "12078",
        "12351",
        "82521",
        "66389",
        "82711",
        "85903",
        "12128",
        "48898",
        "20843",
        "58240",
        "68429",
        "59096",
        "53560",
        "93193",
        "69411",
        "26227",
        "71063",
        "67115",
        "88324",
        "32275",
        "82089",
        "15976",
        "67182",
        "49766",
        "63584",
        "49914",
        "75478",
        "49144",
        "46637",
        "73635",
        "83898",
        "81190",
        "36791",
        "26973",
        "43017",
        "43437",
        "36446",
        "81105",
        "46715",
        "85215",
        "69537",
        "75958",
        "86280",
        "43195",
        "61563",
        "44910",
        "45177",
        "39448",
        "86582",
        "97686",
        "48055",
        "33324",
        "57796",
        "69494",
        "52785"
    ],
    "calendar": {
        "3f926": [
            [
                0,
                650
            ]
        ],
        "93239": [
            [
                0,
                650
            ]
        ],
        "a80d7": [
            [
                0,
                650
            ]
        ],
        "bbed0": [
            [
                0,
                650
            ]
        ],
        "80258": [
            [
                0,
                650
            ]
        ],
        "8533f": [
            [
                0,
                650
            ]
        ],
        "b8747": [
            [
                0,
                650
            ]
        ],
        "f7b98": [
            [
                0,
                650
            ]
        ],
        "830b6": [
            [
                0,
                650
            ]
        ],
        "ab78a": [
            [
                0,
                650
            ]
        ],
        "9ef6a": [
            [
                0,
                650
            ]
        ],
        "414c9": [
            [
                0,
                650
            ]
        ],
        "2923b": [
            [
                0,
                650
            ]
        ],
        "46a8d": [
            [
                0,
                650
            ]
        ],
        "1e5be": [
            [
                0,
                650
            ]
        ],
        "6615f": [
            [
                0,
                650
            ]
        ],
        "e269b": [
            [
                0,
                1021125
            ]
        ],
        "111a9": [
            [
                0,
                1021125
            ]
        ]
    },
    "teams_to_index": {
        "e269b": 0,
        "2923b": 1,
        "46a8d": 2,
        "9ef6a": 3,
        "f7b98": 4,
        "bbed0": 5,
        "93239": 6,
        "a80d7": 7,
        "80258": 8,
        "ab78a": 9,
        "6615f": 10,
        "3f926": 11,
        "1e5be": 12,
        "414c9": 13,
        "b8747": 14,
        "830b6": 15,
        "8533f": 16
    },
    "tasks_data": {
        "14868": {
            "duration": 15
        },
        "31859": {
            "duration": 30
        },
        "92149": {
            "duration": 15
        },
        "56141": {
            "duration": 45
        },
        "77346": {
            "duration": 15
        },
        "45902": {
            "duration": 45
        },
        "50400": {
            "duration": 45
        },
        "82146": {
            "duration": 60
        },
        "93256": {
            "duration": 15
        },
        "19282": {
            "duration": 15
        },
        "51523": {
            "duration": 30
        },
        "47020": {
            "duration": 15
        },
        "22302": {
            "duration": 30
        },
        "22540": {
            "duration": 45
        },
        "80295": {
            "duration": 15
        },
        "15242": {
            "duration": 30
        },
        "12121": {
            "duration": 15
        },
        "99407": {
            "duration": 30
        },
        "36266": {
            "duration": 30
        },
        "66962": {
            "duration": 60
        },
        "96942": {
            "duration": 75
        },
        "90528": {
            "duration": 30
        },
        "20328": {
            "duration": 15
        },
        "88985": {
            "duration": 15
        },
        "78704": {
            "duration": 45
        },
        "12078": {
            "duration": 15
        },
        "12351": {
            "duration": 30
        },
        "82521": {
            "duration": 15
        },
        "66389": {
            "duration": 30
        },
        "82711": {
            "duration": 15
        },
        "85903": {
            "duration": 15
        },
        "12128": {
            "duration": 15
        },
        "48898": {
            "duration": 60
        },
        "20843": {
            "duration": 45
        },
        "58240": {
            "duration": 60
        },
        "68429": {
            "duration": 30
        },
        "59096": {
            "duration": 15
        },
        "53560": {
            "duration": 15
        },
        "93193": {
            "duration": 15
        },
        "69411": {
            "duration": 15
        },
        "26227": {
            "duration": 30
        },
        "71063": {
            "duration": 15
        },
        "67115": {
            "duration": 45
        },
        "88324": {
            "duration": 45
        },
        "32275": {
            "duration": 15
        },
        "82089": {
            "duration": 90
        },
        "15976": {
            "duration": 30
        },
        "67182": {
            "duration": 15
        },
        "49766": {
            "duration": 75
        },
        "63584": {
            "duration": 15
        },
        "49914": {
            "duration": 45
        },
        "75478": {
            "duration": 30
        },
        "49144": {
            "duration": 30
        },
        "46637": {
            "duration": 45
        },
        "73635": {
            "duration": 15
        },
        "83898": {
            "duration": 15
        },
        "81190": {
            "duration": 15
        },
        "36791": {
            "duration": 30
        },
        "26973": {
            "duration": 15
        },
        "43017": {
            "duration": 15
        },
        "43437": {
            "duration": 15
        },
        "36446": {
            "duration": 15
        },
        "81105": {
            "duration": 30
        },
        "46715": {
            "duration": 45
        },
        "85215": {
            "duration": 15
        },
        "69537": {
            "duration": 30
        },
        "75958": {
            "duration": 45
        },
        "86280": {
            "duration": 30
        },
        "43195": {
            "duration": 15
        },
        "61563": {
            "duration": 15
        },
        "44910": {
            "duration": 45
        },
        "45177": {
            "duration": 30
        },
        "39448": {
            "duration": 15
        },
        "86582": {
            "duration": 15
        },
        "97686": {
            "duration": 15
        },
        "48055": {
            "duration": 15
        },
        "33324": {
            "duration": 15
        },
        "57796": {
            "duration": 15
        },
        "69494": {
            "duration": 30
        },
        "52785": {
            "duration": 30
        }
    },
    "same_allocation": [
        [
            "77346",
            "19282"
        ],
        [
            "19282",
            "15242"
        ],
        [
            "22302",
            "36266"
        ],
        [
            "82089",
            "75478"
        ],
        [
            "63584",
            "73635"
        ],
        [
            "73635",
            "26973"
        ],
        [
            "36446",
            "26973"
        ],
        [
            "36446",
            "85215"
        ],
        [
            "43195",
            "85215"
        ],
        [
            "43195",
            "39448"
        ],
        [
            "97686",
            "39448"
        ],
        [
            "97686",
            "33324"
        ],
        [
            "57796",
            "33324"
        ],
        [
            "43017",
            "44910"
        ]
    ],
    "compatible_teams": {
        "51523": [
            "93239",
            "3f926"
        ]
    },
    "start_window": {
        "31859": [
            0,
            30.0
        ],
        "56141": [
            0,
            30.0
        ],
        "82146": [
            0,
            30.0
        ],
        "45902": [
            0,
            32.0
        ],
        "50400": [
            0,
            36.0
        ],
        "14868": [
            0,
            43.0
        ],
        "92149": [
            0,
            59.0
        ],
        "77346": [
            1.0,
            61.0
        ],
        "93256": [
            15.0,
            75.0
        ],
        "51523": [
            15.0,
            75.0
        ],
        "22540": [
            16.0,
            76.0
        ],
        "19282": [
            17.0,
            77.0
        ],
        "96942": [
            19.0,
            79.0
        ],
        "22302": [
            22.0,
            82.0
        ],
        "47020": [
            31.0,
            91.0
        ],
        "66962": [
            31.0,
            91.0
        ],
        "15242": [
            33.0,
            93.0
        ],
        "80295": [
            47.0,
            107.0
        ],
        "99407": [
            50.0,
            110.0
        ],
        "36266": [
            53.0,
            113.0
        ],
        "78704": [
            62.0,
            122.0
        ],
        "12121": [
            63.0,
            123.0
        ],
        "90528": [
            64.0,
            124.0
        ],
        "20328": [
            79.0,
            139.0
        ],
        "12351": [
            84.0,
            144.0
        ],
        "88985": [
            89.0,
            149.0
        ],
        "48898": [
            92.0,
            152.0
        ],
        "12078": [
            95.0,
            155.0
        ],
        "66389": [
            95.0,
            155.0
        ],
        "58240": [
            95.0,
            155.0
        ],
        "82521": [
            106.0,
            166.0
        ],
        "20843": [
            108.0,
            168.0
        ],
        "82711": [
            111.0,
            171.0
        ],
        "85903": [
            115.0,
            175.0
        ],
        "82089": [
            122.0,
            182.0
        ],
        "68429": [
            126.0,
            186.0
        ],
        "12128": [
            127.0,
            187.0
        ],
        "59096": [
            143.0,
            203.0
        ],
        "53560": [
            151.0,
            211.0
        ],
        "67115": [
            153.0,
            213.0
        ],
        "88324": [
            154.0,
            214.0
        ],
        "49766": [
            156.0,
            216.0
        ],
        "26227": [
            157.0,
            217.0
        ],
        "93193": [
            159.0,
            219.0
        ],
        "69411": [
            167.0,
            227.0
        ],
        "71063": [
            175.0,
            235.0
        ],
        "15976": [
            183.0,
            243.0
        ],
        "32275": [
            191.0,
            251.0
        ],
        "49914": [
            199.0,
            259.0
        ],
        "46637": [
            200.0,
            260.0
        ],
        "67182": [
            207.0,
            267.0
        ],
        "75478": [
            214.0,
            274.0
        ],
        "49144": [
            214.0,
            274.0
        ],
        "63584": [
            223.0,
            283.0
        ],
        "36791": [
            233.0,
            293.0
        ],
        "73635": [
            239.0,
            299.0
        ],
        "83898": [
            246.0,
            306.0
        ],
        "81190": [
            246.0,
            306.0
        ],
        "26973": [
            255.0,
            315.0
        ],
        "46715": [
            257.0,
            317.0
        ],
        "43017": [
            262.0,
            322.0
        ],
        "75958": [
            262.0,
            322.0
        ],
        "43437": [
            264.0,
            324.0
        ],
        "81105": [
            264.0,
            324.0
        ],
        "36446": [
            271.0,
            331.0
        ],
        "69537": [
            274.0,
            334.0
        ],
        "44910": [
            278.0,
            338.0
        ],
        "86280": [
            281.0,
            341.0
        ],
        "85215": [
            287.0,
            347.0
        ],
        "45177": [
            302.0,
            362.0
        ],
        "43195": [
            303.0,
            363.0
        ],
        "61563": [
            305.0,
            365.0
        ],
        "39448": [
            319.0,
            379.0
        ],
        "86582": [
            321.0,
            381.0
        ],
        "97686": [
            335.0,
            395.0
        ],
        "48055": [
            337.0,
            397.0
        ],
        "33324": [
            351.0,
            411.0
        ],
        "57796": [
            367.0,
            427.0
        ],
        "69494": [
            374.0,
            434.0
        ],
        "52785": [
            390.0,
            450.0
        ]
    },
    "end_window": {
        "31859": [
            0,
            60.0
        ],
        "56141": [
            15.0,
            75.0
        ],
        "82146": [
            30.0,
            90.0
        ],
        "45902": [
            17.0,
            77.0
        ],
        "50400": [
            21.0,
            81.0
        ],
        "14868": [
            0,
            58.0
        ],
        "92149": [
            14.0,
            74.0
        ],
        "77346": [
            16.0,
            76.0
        ],
        "93256": [
            30.0,
            90.0
        ],
        "51523": [
            45.0,
            105.0
        ],
        "22540": [
            61.0,
            121.0
        ],
        "19282": [
            32.0,
            92.0
        ],
        "96942": [
            94.0,
            154.0
        ],
        "22302": [
            52.0,
            112.0
        ],
        "47020": [
            46.0,
            106.0
        ],
        "66962": [
            91.0,
            151.0
        ],
        "15242": [
            63.0,
            123.0
        ],
        "80295": [
            62.0,
            122.0
        ],
        "99407": [
            80.0,
            140.0
        ],
        "36266": [
            83.0,
            143.0
        ],
        "78704": [
            107.0,
            167.0
        ],
        "12121": [
            78.0,
            138.0
        ],
        "90528": [
            94.0,
            154.0
        ],
        "20328": [
            94.0,
            154.0
        ],
        "12351": [
            114.0,
            174.0
        ],
        "88985": [
            104.0,
            164.0
        ],
        "48898": [
            152.0,
            212.0
        ],
        "12078": [
            110.0,
            170.0
        ],
        "66389": [
            125.0,
            185.0
        ],
        "58240": [
            155.0,
            215.0
        ],
        "82521": [
            121.0,
            181.0
        ],
        "20843": [
            153.0,
            213.0
        ],
        "82711": [
            126.0,
            186.0
        ],
        "85903": [
            130.0,
            190.0
        ],
        "82089": [
            212.0,
            272.0
        ],
        "68429": [
            156.0,
            216.0
        ],
        "12128": [
            142.0,
            202.0
        ],
        "59096": [
            158.0,
            218.0
        ],
        "53560": [
            166.0,
            226.0
        ],
        "67115": [
            198.0,
            258.0
        ],
        "88324": [
            199.0,
            259.0
        ],
        "49766": [
            231.0,
            291.0
        ],
        "26227": [
            187.0,
            247.0
        ],
        "93193": [
            174.0,
            234.0
        ],
        "69411": [
            182.0,
            242.0
        ],
        "71063": [
            190.0,
            250.0
        ],
        "15976": [
            213.0,
            273.0
        ],
        "32275": [
            206.0,
            266.0
        ],
        "49914": [
            244.0,
            304.0
        ],
        "46637": [
            245.0,
            305.0
        ],
        "67182": [
            222.0,
            282.0
        ],
        "75478": [
            244.0,
            304.0
        ],
        "49144": [
            244.0,
            304.0
        ],
        "63584": [
            238.0,
            298.0
        ],
        "36791": [
            263.0,
            323.0
        ],
        "73635": [
            254.0,
            314.0
        ],
        "83898": [
            261.0,
            321.0
        ],
        "81190": [
            261.0,
            321.0
        ],
        "26973": [
            270.0,
            330.0
        ],
        "46715": [
            302.0,
            362.0
        ],
        "43017": [
            277.0,
            337.0
        ],
        "75958": [
            307.0,
            367.0
        ],
        "43437": [
            279.0,
            339.0
        ],
        "81105": [
            294.0,
            354.0
        ],
        "36446": [
            286.0,
            346.0
        ],
        "69537": [
            304.0,
            364.0
        ],
        "44910": [
            323.0,
            383.0
        ],
        "86280": [
            311.0,
            371.0
        ],
        "85215": [
            302.0,
            362.0
        ],
        "45177": [
            332.0,
            392.0
        ],
        "43195": [
            318.0,
            378.0
        ],
        "61563": [
            320.0,
            380.0
        ],
        "39448": [
            334.0,
            394.0
        ],
        "86582": [
            336.0,
            396.0
        ],
        "97686": [
            350.0,
            410.0
        ],
        "48055": [
            352.0,
            412.0
        ],
        "33324": [
            366.0,
            426.0
        ],
        "57796": [
            382.0,
            442.0
        ],
        "69494": [
            404.0,
            464.0
        ],
        "52785": [
            420.0,
            480.0
        ]
    },
    "successors": {
        "81190": [
            "43017"
        ],
        "43017": [
            "44910"
        ],
        "36791": [
            "81105"
        ],
        "77346": [
            "19282"
        ],
        "19282": [
            "15242"
        ],
        "88985": [
            "82521"
        ],
        "82521": [
            "82089"
        ],
        "82089": [
            "75478"
        ],
        "75478": [
            "83898"
        ],
        "83898": [
            "43437"
        ],
        "43437": [
            "86280"
        ],
        "93256": [
            "12078"
        ],
        "12078": [
            "71063",
            "26973"
        ],
        "26973": [
            "97686"
        ],
        "22302": [
            "36266"
        ],
        "50400": [
            "85903"
        ],
        "12351": [
            "53560"
        ],
        "53560": [
            "69411"
        ],
        "69411": [
            "15976"
        ],
        "15976": [
            "49144"
        ],
        "14868": [
            "12121"
        ],
        "12121": [
            "63584",
            "59096"
        ],
        "63584": [
            "85215"
        ],
        "80295": [
            "12128"
        ],
        "12128": [
            "43195",
            "67182"
        ],
        "43195": [
            "57796"
        ],
        "92149": [
            "20328"
        ],
        "20328": [
            "73635",
            "93193"
        ],
        "73635": [
            "39448"
        ],
        "47020": [
            "82711"
        ],
        "82711": [
            "36446",
            "32275"
        ],
        "36446": [
            "33324"
        ]
    },
    "horizon_shift": 1754776800,
    "original_start": {
        "31859": 0.0,
        "56141": 0.0,
        "82146": 0.0,
        "45902": 2.0,
        "50400": 6.0,
        "14868": 13.0,
        "92149": 29.0,
        "77346": 31.0,
        "93256": 45.0,
        "51523": 45.0,
        "22540": 46.0,
        "19282": 47.0,
        "96942": 49.0,
        "22302": 52.0,
        "47020": 61.0,
        "66962": 61.0,
        "15242": 63.0,
        "80295": 77.0,
        "99407": 80.0,
        "36266": 83.0,
        "78704": 92.0,
        "12121": 93.0,
        "90528": 94.0,
        "20328": 109.0,
        "12351": 114.0,
        "88985": 119.0,
        "48898": 122.0,
        "12078": 125.0,
        "66389": 125.0,
        "58240": 125.0,
        "82521": 136.0,
        "20843": 138.0,
        "82711": 141.0,
        "85903": 145.0,
        "82089": 152.0,
        "68429": 156.0,
        "12128": 157.0,
        "59096": 173.0,
        "53560": 181.0,
        "67115": 183.0,
        "88324": 184.0,
        "49766": 186.0,
        "26227": 187.0,
        "93193": 189.0,
        "69411": 197.0,
        "71063": 205.0,
        "15976": 213.0,
        "32275": 221.0,
        "49914": 229.0,
        "46637": 230.0,
        "67182": 237.0,
        "75478": 244.0,
        "49144": 244.0,
        "63584": 253.0,
        "36791": 263.0,
        "73635": 269.0,
        "83898": 276.0,
        "81190": 276.0,
        "26973": 285.0,
        "46715": 287.0,
        "43017": 292.0,
        "75958": 292.0,
        "43437": 294.0,
        "81105": 294.0,
        "36446": 301.0,
        "69537": 304.0,
        "44910": 308.0,
        "86280": 311.0,
        "85215": 317.0,
        "45177": 332.0,
        "43195": 333.0,
        "61563": 335.0,
        "39448": 349.0,
        "86582": 351.0,
        "97686": 365.0,
        "48055": 367.0,
        "33324": 381.0,
        "57796": 397.0,
        "69494": 404.0,
        "52785": 420.0
    },
    "original_end": {
        "31859": 30.0,
        "56141": 45.0,
        "82146": 60.0,
        "45902": 47.0,
        "50400": 51.0,
        "14868": 28.0,
        "92149": 44.0,
        "77346": 46.0,
        "93256": 60.0,
        "51523": 75.0,
        "22540": 91.0,
        "19282": 62.0,
        "96942": 124.0,
        "22302": 82.0,
        "47020": 76.0,
        "66962": 121.0,
        "15242": 93.0,
        "80295": 92.0,
        "99407": 110.0,
        "36266": 113.0,
        "78704": 137.0,
        "12121": 108.0,
        "90528": 124.0,
        "20328": 124.0,
        "12351": 144.0,
        "88985": 134.0,
        "48898": 182.0,
        "12078": 140.0,
        "66389": 155.0,
        "58240": 185.0,
        "82521": 151.0,
        "20843": 183.0,
        "82711": 156.0,
        "85903": 160.0,
        "82089": 242.0,
        "68429": 186.0,
        "12128": 172.0,
        "59096": 188.0,
        "53560": 196.0,
        "67115": 228.0,
        "88324": 229.0,
        "49766": 261.0,
        "26227": 217.0,
        "93193": 204.0,
        "69411": 212.0,
        "71063": 220.0,
        "15976": 243.0,
        "32275": 236.0,
        "49914": 274.0,
        "46637": 275.0,
        "67182": 252.0,
        "75478": 274.0,
        "49144": 274.0,
        "63584": 268.0,
        "36791": 293.0,
        "73635": 284.0,
        "83898": 291.0,
        "81190": 291.0,
        "26973": 300.0,
        "46715": 332.0,
        "43017": 307.0,
        "75958": 337.0,
        "43437": 309.0,
        "81105": 324.0,
        "36446": 316.0,
        "69537": 334.0,
        "44910": 353.0,
        "86280": 341.0,
        "85215": 332.0,
        "45177": 362.0,
        "43195": 348.0,
        "61563": 350.0,
        "39448": 364.0,
        "86582": 366.0,
        "97686": 380.0,
        "48055": 382.0,
        "33324": 396.0,
        "57796": 412.0,
        "69494": 434.0,
        "52785": 450.0
    }
}